hugdatafast/__init__.py
hugdatafast/fastai.py
hugdatafast/transform.py
hugdatafast-1.0.0.dist-info/LICENSE
hugdatafast-1.0.0.dist-info/METADATA
hugdatafast-1.0.0.dist-info/WHEEL
hugdatafast-1.0.0.dist-info/top_level.txt
hugdatafast-1.0.0.dist-info/RECORD
