Metadata-Version: 2.1
Name: hugdatafast
Version: 1.0.0
Summary: The elegant bridge between hugginface data and fastai
Home-page: https://github.com/richarddwang/hugdatafast
Author: Richard Wang
Author-email: richardyy1188@gmail.com
License: Apache 2.0
Keywords: datasets machine learning datasets metrics fastai huggingface
Platform: UNKNOWN
Classifier: Development Status :: 4 - Beta
Classifier: Intended Audience :: Developers
Classifier: Intended Audience :: Science/Research
Classifier: Programming Language :: Python :: 3
Classifier: License :: OSI Approved :: Apache Software License
Classifier: Operating System :: OS Independent
Classifier: Topic :: Scientific/Engineering :: Artificial Intelligence
Requires-Python: >=3.6
Requires-Dist: fastai (>=2.0.8)
Requires-Dist: fastscore (>=1.0.1)
Requires-Dist: datasets
